rispack/__init__.py
rispack/actions.py
rispack/aws.py
rispack/database.py
rispack/entities.py
rispack/entrypoint.py
rispack/errors.py
rispack/events.py
rispack/handler/__init__.py
rispack/handler/interceptors/__init__.py
rispack/handler/interceptors/base.py
rispack/handler/interceptors/otp.py
rispack/handler/interceptors/pin.py
rispack/handler/interceptors/role.py
rispack/handler/interceptors/scope.py
rispack/handler/interceptors/token.py
rispack/handler/job.py
rispack/handler/record.py
rispack/handler/request.py
rispack/handler/response.py
rispack/handler/route.py
rispack/logger.py
rispack/schemas.py
rispack/stores.py
rispack-1.2.2.dist-info/LICENSE
rispack-1.2.2.dist-info/METADATA
rispack-1.2.2.dist-info/WHEEL
rispack-1.2.2.dist-info/RECORD
