Metadata-Version: 2.1
Name: rispack
Version: 1.2.2
Summary: Pack of shared libraries from Rispar
License: MIT
Author: Rispar
Author-email: tecnologia@rispar.com.br
Requires-Python: >=3.12,<4.0
Classifier: License :: OSI Approved :: MIT License
Classifier: Programming Language :: Python :: 3
Classifier: Programming Language :: Python :: 3.12
Requires-Dist: SQLAlchemy (>=1.4.36,<2.0.0)
Requires-Dist: aws-lambda-powertools (>=2.34.2,<3.0.0)
Requires-Dist: boto3 (>=1.34.52,<2.0.0)
Requires-Dist: marshmallow (>=3.21.0,<4.0.0)
Requires-Dist: marshmallow-dataclass (>=8.6.0,<9.0.0)
Requires-Dist: marshmallow-enum (>=1.5.1,<2.0.0)
Requires-Dist: pg8000 (>=1.30.5,<2.0.0)
Requires-Dist: requests (>=2.31.0,<3.0.0)
Requires-Dist: requests-aws-sign (>=0.1.6,<0.2.0)
